{
    "portals": {
        "dashboard": "",
        "volume": "",
        "media": "",
        "processes": "",
        "language": "",
        "main_menu": ""
    },
    "menu": {
        "refresh": "",
        "new": "",
        "plugins": "",
        "management": "",
        "renew_token": "",
        "remove_session": "",
        "establish_session": "",
        "sign_out": "",
        "sign_in": "",
        "view_source": "",
        "filter": "",
        "blur": "",
        "sort": "",
        "edit": "",
        "info_url": "",
        "new_folder": "",
        "edit_folder": "",
        "delete_folder": "",
        "folder": "",
        "refresh_options": ""
    },
    "menu_new": {
        "book": "",
        "group": "",
        "user": ""
    },
    "menu_manage": {
        "change_password": "",
        "view_hard_sessions": "",
        "user_listing": "",
        "group_listing": "",
        "property_listing": "",
        "manage_hard_sessions": "",
        "restart_server": "",
        "stop_server": ""
    },
    "menu_plugins": {
        "general": "",
        "utility": "",
        "books": "",
        "media": ""
    },
    "langs": {
        "en": "",
        "fr": "",
        "es": "",
        "de": "",
        "test": ""
    },
    "form": {
        "back_to_chapters": "",
        "chapter_listing": "",
        "book_details": "",
        "id": "",
        "name": "",
        "source": "",
        "display_style": "",
        "rating": "",
        "rating_g": "",
        "rating_pg": "",
        "rating_pg13": "",
        "rating_r17": "",
        "rating_rplus": "",
        "rating_rx": "",
        "rating_unrated": "",
        "status": "",
        "skip_chapters": "",
        "info_url": "",
        "rss_url": "",
        "extra_url": "",
        "start_chapter": "",
        "tags": "",
        "book_entry": "",
        "text_filter": "",
        "sort_az": "",
        "sort_za": "",
        "sort_da": "",
        "sort_dd": "",
        "new_book": "",
        "done_book": "",
        "more_book": "",
        "no_data": "",
        "change_password": "",
        "current_password": "",
        "new_password": "",
        "again_password": "",
        "previous_chapter": "",
        "next_chapter": "",
        "merge_image": "",
        "auto_merge_image": "",
        "select_image": "",
        "split_image": "",
        "delete_image": "",
        "edit_chapter": "",
        "storage_overview": "",
        "value": "",
        "group_entry": "",
        "group": "",
        "description": "",
        "sessionid": "",
        "userid": "",
        "created": "",
        "last_date": "",
        "expired_date": "",
        "to_page_mode": "",
        "to_scroll_mode": "",
        "login": "",
        "email": "",
        "password": "",
        "hard_session_auth": "",
        "session_pin": "",
        "login_pin": "",
        "root": "",
        "sort_sa": "",
        "sort_sd": "",
        "primary_storage": "",
        "archive_storage": "",
        "edit_folder": "",
        "mime_type": "",
        "filesize": "",
        "location": "",
        "has_preview": "",
        "owning_group": "",
        "process_details": "",
        "task_logging": "",
        "time": "",
        "message": "",
        "process_level": "",
        "details": "",
        "initilization": "",
        "delay": "",
        "start": "",
        "running": "",
        "finish": "",
        "total": "",
        "task_information": "",
        "process_listing": "",
        "progress": "",
        "process_id": "",
        "task_name": "",
        "task_id": "",
        "task_status_percents": "",
        "task_status": "",
        "primary_progress": "",
        "sub_progress": "",
        "edit_property": "",
        "property_id": "",
        "comment": "",
        "recent_media": "",
        "recent_books": "",
        "user_entry": "",
        "username": "",
        "book_limit": "",
        "media_limit": "",
        "features": "",
        "wait_for_server": ""
    },
    "action": {
        "books": "",
        "bookmarks": "",
        "delete": "",
        "grid_view": "",
        "list_view": "",
        "auto_next": "",
        "sub_menu": "",
        "delete_selected": "",
        "view": "",
        "chapters": "",
        "create": "",
        "split_view": "",
        "selection_mode": "",
        "select_all": "",
        "download_selected": "",
        "plugin_actions": "",
        "archive_selected": "",
        "activate": "",
        "inactivate": "",
        "mark_watched": "",
        "mark_new": "",
        "move_selected": "",
        "edit_file": "",
        "delete_file": "",
        "download": "",
        "update": "",
        "previous_item": "",
        "next_item": "",
        "random": "",
        "season": "",
        "episode": "",
        "english": "",
        "japanese": "",
        "chinese": "",
        "execute": "",
        "reset": "",
        "refresh": "",
        "cancel": "",
        "promote": "",
        "close": "",
        "toogle_auto_refresh": "",
        "just_refresh": "",
        "hard_clean": "",
        "soft_clean": "",
        "view_details": ""
    },
    "option": {
        "offline": "",
        "page_based": "",
        "scolling_based": "",
        "inactive_item": "",
        "active_item": "",
        "no": "",
        "yes": "",
        "inactive": "",
        "active": "",
        "none": "",
        "critical": "",
        "error": "",
        "warning": "",
        "info": "",
        "debug": "",
        "trace": ""
    },
    "app": {
        "title": ""
    }
}